odoo/addons/partner_contact_type_end_user/README.rst
odoo/addons/partner_contact_type_end_user/__init__.py
odoo/addons/partner_contact_type_end_user/__manifest__.py
odoo/addons/partner_contact_type_end_user/i18n/it.po
odoo/addons/partner_contact_type_end_user/i18n/nl.po
odoo/addons/partner_contact_type_end_user/i18n/partner_contact_type_end_user.pot
odoo/addons/partner_contact_type_end_user/models/__init__.py
odoo/addons/partner_contact_type_end_user/models/res_partner.py
odoo/addons/partner_contact_type_end_user/readme/CONTRIBUTORS.md
odoo/addons/partner_contact_type_end_user/readme/DESCRIPTION.md
odoo/addons/partner_contact_type_end_user/static/description/icon.png
odoo/addons/partner_contact_type_end_user/static/description/index.html
odoo/addons/partner_contact_type_end_user/tests/__init__.py
odoo/addons/partner_contact_type_end_user/tests/test_partner_contact_type_end_user.py
odoo_addon_partner_contact_type_end_user-18.0.1.0.0.4.dist-info/METADATA
odoo_addon_partner_contact_type_end_user-18.0.1.0.0.4.dist-info/WHEEL
odoo_addon_partner_contact_type_end_user-18.0.1.0.0.4.dist-info/top_level.txt
odoo_addon_partner_contact_type_end_user-18.0.1.0.0.4.dist-info/RECORD
